{"cameraMode":{"drawMode":0,"name":"Shaded","section":"Shading Mode"},"sceneLighting":true,"audioPlay":false,"sceneViewState":{"showFog":true,"showMaterialUpdate":false,"showSkybox":true,"showFlares":true,"showImageEffects":true,"showParticleSystems":true},"in2DMode":false,"pivot":{"x":46.04631805419922,"y":-39.744911193847659,"z":-102.60130310058594},"rotation":{"x":0.18910415470600129,"y":-0.769610583782196,"z":0.2845306098461151,"w":0.5407756567001343},"size":109.14447021484375,"orthographic":false}