{"cameraMode":{"drawMode":0,"name":"Shaded","section":"Shading Mode"},"sceneLighting":true,"audioPlay":false,"sceneViewState":{"showFog":true,"showMaterialUpdate":false,"showSkybox":true,"showFlares":true,"showImageEffects":true,"showParticleSystems":true},"in2DMode":false,"pivot":{"x":77.47992706298828,"y":27.80634880065918,"z":-45.594886779785159},"rotation":{"x":-0.076021209359169,"y":-0.8183104395866394,"z":0.11729881167411804,"w":-0.5611940622329712},"size":38.90793991088867,"orthographic":false}